PyNaver/__init__.py
PyNaver/api.py
PyNaver/config/__init__.py
PyNaver/config/info.py
PyNaver-0.0.10.dist-info/LICENSE
PyNaver-0.0.10.dist-info/METADATA
PyNaver-0.0.10.dist-info/WHEEL
PyNaver-0.0.10.dist-info/top_level.txt
PyNaver-0.0.10.dist-info/RECORD
